XOR-cipher/__init__.py
XOR-cipher/encrypt.py
xor_cipher/__init__.py
xor_cipher/encrypt.py
xor_cipher_pikicode-0.0.1.dist-info/LICENSE
xor_cipher_pikicode-0.0.1.dist-info/METADATA
xor_cipher_pikicode-0.0.1.dist-info/WHEEL
xor_cipher_pikicode-0.0.1.dist-info/top_level.txt
xor_cipher_pikicode-0.0.1.dist-info/RECORD
